mt/streamz/__init__.py
mt/streamz/core.py
mt/streamz/dask.py
mt/streamz/index.py
mt/streamz/version.py
mtstreamz-0.2.1.dist-info/LICENSE
mtstreamz-0.2.1.dist-info/METADATA
mtstreamz-0.2.1.dist-info/WHEEL
mtstreamz-0.2.1.dist-info/top_level.txt
mtstreamz-0.2.1.dist-info/RECORD
