Metadata-Version: 2.1
Name: mtstreamz
Version: 0.2.1
Summary: Minh-Tri Pham's extension of the streamz Python library
Home-page: https://github.com/inteplus/mtstreamz
Author: ['Minh-Tri Pham']
Project-URL: Documentation, https://mtdoc.readthedocs.io/en/latest/mt.streamz/mt.streamz.html
Project-URL: Source Code, https://github.com/inteplus/mtstreamz
License-File: LICENSE
Requires-Dist: tornado (>=6.0.4)
Requires-Dist: dask (>=2.24.0)
Requires-Dist: distributed (>=2.24.0)
Requires-Dist: streamz (>=0.5.5)
Requires-Dist: mtbase (>=1.0.0)
